<?xml version="1.0" encoding="utf-8"?>
<!DOCTYPE hibernate-mapping PUBLIC "-//Hibernate/Hibernate Mapping DTD 3.0//EN"
"http://hibernate.sourceforge.net/hibernate-mapping-3.0.dtd">
<!-- 
    Mapping file autogenerated by MyEclipse Persistence Tools
-->
<hibernate-mapping>
    <class name="com.pojo.Areas" table="areas" >
        <id name="areaId" type="java.lang.Integer">
            <column name="areaId" />
            <generator class="native" />
        </id>
        <many-to-one name="citys" class="com.pojo.Citys" fetch="select">
            <column name="cityId" not-null="true">
                <comment>市ID</comment>
            </column>
        </many-to-one>
        <property name="areaName" type="java.lang.String">
            <column name="areaName" length="50" not-null="true">
                <comment>区县名称</comment>
            </column>
        </property>
        <set name="addresses" inverse="true">
            <key>
                <column name="areaId" not-null="true">
                    <comment>区县 ID</comment>
                </column>
            </key>
            <one-to-many class="com.pojo.Address" />
        </set>
    </class>
</hibernate-mapping>
